LICENSE
MANIFEST.in
README.md
setup.py
threedb/__init__.py
threedb/client.py
threedb/main.py
threedb/try_bpy.py
threedb/utils.py
threedb/controls/__init__.py
threedb/controls/base_control.py
threedb/controls/blender/__init__.py
threedb/controls/blender/background.py
threedb/controls/blender/camera.py
threedb/controls/blender/denoiser.py
threedb/controls/blender/imagenet_c.py
threedb/controls/blender/material.py
threedb/controls/blender/mug_liquid.py
threedb/controls/blender/obj_loc_in_frame.py
threedb/controls/blender/occlusion.py
threedb/controls/blender/orientation.py
threedb/controls/blender/pin_to_ground.py
threedb/controls/blender/pointlight.py
threedb/controls/blender/position.py
threedb/controls/blender/scale.py
threedb/controls/blender/utils.py
threedb/evaluators/__init__.py
threedb/evaluators/base_evaluator.py
threedb/evaluators/classification.py
threedb/evaluators/detection.py
threedb/policies/__init__.py
threedb/policies/grid_search.py
threedb/policies/random_search.py
threedb/rendering/__init__.py
threedb/rendering/base_renderer.py
threedb/rendering/render_blender.py
threedb/rendering/utils.py
threedb/result_logging/__init__.py
threedb/result_logging/base_logger.py
threedb/result_logging/image_logger.py
threedb/result_logging/json_logger.py
threedb/result_logging/logger_manager.py
threedb/result_logging/tb_logger.py
threedb/scheduling/__init__.py
threedb/scheduling/base_scheduler.py
threedb/scheduling/policy_controller.py
threedb/scheduling/search_space.py
threedb/scheduling/utils.py
threedb_preview.egg-info/PKG-INFO
threedb_preview.egg-info/SOURCES.txt
threedb_preview.egg-info/dependency_links.txt
threedb_preview.egg-info/not-zip-safe
threedb_preview.egg-info/requires.txt
threedb_preview.egg-info/top_level.txt