Metadata-Version: 2.1
Name: threedb-preview
Version: 0.0.8
Summary: A framework for analyzing computer vision models with simulated data 
Home-page: https://github.com/3db/3db
Author: 3DB authors
Author-email: leclerc@mit.edu
License: MIT
Platform: UNKNOWN
